dbhose_utils/__init__.py
dbhose_utils/common.cpython-314-x86_64-linux-gnu.so
dbhose_utils/common.pxd
dbhose_utils/common.pyi
dbhose_utils/common.pyx
dbhose_utils/convertor.py
dbhose_utils/detective.py
dbhose_utils/recovery.py
dbhose_utils-0.0.2.4.dist-info/METADATA
dbhose_utils-0.0.2.4.dist-info/WHEEL
dbhose_utils-0.0.2.4.dist-info/top_level.txt
dbhose_utils-0.0.2.4.dist-info/RECORD
dbhose_utils-0.0.2.4.dist-info/licenses/LICENSE
