Metadata-Version: 2.4
Name: dbhose_utils
Version: 0.0.2.4
Summary: DBHose dumps convertors utility.
Author-email: 0xMihalich <bayanmobile87@gmail.com>
License: MIT License
Project-URL: Homepage, https://github.com/0xMihalich/dbhose_utils
Project-URL: Documentation, https://github.com/0xMihalich/dbhose_utils#readme
Project-URL: Repository, https://github.com/0xMihalich/dbhose_utils
Project-URL: Changelog, https://github.com/0xMihalich/dbhose_utils/blob/main/CHANGELOG.md
Classifier: Development Status :: 3 - Alpha
Classifier: Intended Audience :: Developers
Classifier: Programming Language :: Python :: 3.10
Classifier: Programming Language :: Python :: 3.11
Classifier: Programming Language :: Python :: 3.12
Classifier: Programming Language :: Python :: 3.13
Classifier: Programming Language :: Python :: 3.14
Requires-Python: >=3.10
License-File: LICENSE
Requires-Dist: light-compressor==0.0.2.1
Requires-Dist: nativelib==0.2.2.5
Requires-Dist: pgcopylib==0.2.3.2
Requires-Dist: pgpack==0.3.2.2
Dynamic: license-file
